{
  "parent": "minecraft:recipes/root",
  "criteria": {
    "has_rough_opal_ore": {
      "conditions": {
        "items": [
          {
            "items": [
              "bejeweled:terracotta_opal_ore"
            ]
          }
        ]
      },
      "trigger": "minecraft:inventory_changed"
    },
    "has_the_recipe": {
      "conditions": {
        "recipe": "bejeweled:rough_opal_from_blasting_terracotta_opal_ore"
      },
      "trigger": "minecraft:recipe_unlocked"
    }
  },
  "requirements": [
    [
      "has_rough_opal_ore",
      "has_the_recipe"
    ]
  ],
  "rewards": {
    "recipes": [
      "bejeweled:rough_opal_from_blasting_terracotta_opal_ore"
    ]
  },
  "sends_telemetry_event": false
}